[
  {
    "firstName": "John",
    "lastName": "Smith",
    "nationality": "USA",
    "age": 35,
    "profession": "astronaut"
  },
  {
    "firstName": "Maria",
    "lastName": "Garcia",
    "nationality": "Spain",
    "age": 28,
    "profession": "engineer"
  },
  {
    "firstName": "Yuki",
    "lastName": "Tanaka",
    "nationality": "Japan",
    "age": 40,
    "profession": "astronaut"
  },
  {
    "firstName": "Andre",
    "lastName": "Silva",
    "nationality": "Brazil",
    "age": 45,
    "profession": "doctor"
  },
  {
    "firstName": "Elena",
    "lastName": "Ivanova",
    "nationality": "Russia",
    "age": 32,
    "profession": "engineer"
  },
  {
    "firstName": "Chen",
    "lastName": "Li",
    "nationality": "China",
    "age": 30,
    "profession": "astronaut"
  },
  {
    "firstName": "Luis",
    "lastName": "Lopez",
    "nationality": "Mexico",
    "age": 28,
    "profession": "doctor"
  },
  {
    "firstName": "Aisha",
    "lastName": "Khan",
    "nationality": "Pakistan",
    "age": 35,
    "profession": "engineer"
  },
  {
    "firstName": "Anastasia",
    "lastName": "Sokolov",
    "nationality": "Russia",
    "age": 42,
    "profession": "astronaut"
  },
  {
    "firstName": "Mohammed",
    "lastName": "Abdul",
    "nationality": "Saudi Arabia",
    "age": 38,
    "profession": "doctor"
  },
  {
    "firstName": "Mia",
    "lastName": "Kim",
    "nationality": "South Korea",
    "age": 30,
    "profession": "engineer"
  },
  {
    "firstName": "Lucas",
    "lastName": "Ferreira",
    "nationality": "Brazil",
    "age": 32,
    "profession": "astronaut"
  },
  {
    "firstName": "Amina",
    "lastName": "Ahmed",
    "nationality": "Egypt",
    "age": 28,
    "profession": "doctor"
  },
  {
    "firstName": "Pavel",
    "lastName": "Novak",
    "nationality": "Czech Republic",
    "age": 40,
    "profession": "engineer"
  },
  {
    "firstName": "Nina",
    "lastName": "Jovanovic",
    "nationality": "Serbia",
    "age": 35,
    "profession": "astronaut"
  },
  {
    "firstName": "Carlos",
    "lastName": "Rodriguez",
    "nationality": "Mexico",
    "age": 45,
    "profession": "doctor"
  },
  {
    "firstName": "Hiroshi",
    "lastName": "Yamamoto",
    "nationality": "Japan",
    "age": 32,
    "profession": "engineer"
  },
  {
    "firstName": "Olga",
    "lastName": "Ivanova",
    "nationality": "Russia",
    "age": 28,
    "profession": "astronaut"
  },
  {
    "firstName": "Ricardo",
    "lastName": "Silva",
    "nationality": "Portugal",
    "age": 40,
    "profession": "doctor"
  },
  {
    "firstName": "Li",
    "lastName": "Wei",
    "nationality": "China",
    "age": 35,
    "profession": "engineer"
  },
  {
    "firstName": "Sofia",
    "lastName": "Gomez",
    "nationality": "Colombia",
    "age": 28,
    "profession": "astronaut"
  },
  {
    "firstName": "Ahmed",
    "lastName": "Hassan",
    "nationality": "Egypt",
    "age": 32,
    "profession": "doctor"
  },
  {
    "firstName": "Ji-Hoon",
    "lastName": "Park",
    "nationality": "South Korea",
    "age": 38,
    "profession": "engineer"
  },
  {
    "firstName": "Elena",
    "lastName": "Ivanova",
    "nationality": "Bulgaria",
    "age": 35,
    "profession": "astronaut"
  },
  {
    "firstName": "Joanne",
    "lastName": "Stamm",
    "age": 33,
    "nationality": "Croatia",
    "profession": "doctor"
  },
  {
    "firstName": "Retha",
    "lastName": "Stanton",
    "age": 35,
    "nationality": "Gabon",
    "profession": "doctor"
  },
  {
    "firstName": "Joan",
    "lastName": "Bernhard",
    "age": 32,
    "nationality": "Hong Kong",
    "profession": "astronaut"
  },
  {
    "firstName": "Wilford",
    "lastName": "Hegmann",
    "age": 31,
    "nationality": "Iraq",
    "profession": "doctor"
  },
  {
    "firstName": "Melody",
    "lastName": "Braun",
    "age": 30,
    "nationality": "Suriname",
    "profession": "astronaut"
  },
  {
    "firstName": "Mellie",
    "lastName": "Rowe",
    "age": 38,
    "nationality": "Bermuda",
    "profession": "doctor"
  },
  {
    "firstName": "Mortimer",
    "lastName": "Konopelski",
    "age": 30,
    "nationality": "France",
    "profession": "doctor"
  },
  {
    "firstName": "Marietta",
    "lastName": "Lockman",
    "age": 39,
    "nationality": "Equatorial Guinea",
    "profession": "doctor"
  },
  {
    "firstName": "Alvena",
    "lastName": "Sanford",
    "age": 35,
    "nationality": "Gabon",
    "profession": "astronaut"
  },
  {
    "firstName": "Wallace",
    "lastName": "Kshlerin",
    "age": 32,
    "nationality": "Dominica",
    "profession": "engineer"
  },
  {
    "firstName": "Colby",
    "lastName": "Lakin",
    "age": 39,
    "nationality": "Dominican Republic",
    "profession": "doctor"
  },
  {
    "firstName": "Jaylon",
    "lastName": "Purdy",
    "age": 39,
    "nationality": "Macao",
    "profession": "doctor"
  },
  {
    "firstName": "Destiny",
    "lastName": "Fahey",
    "age": 38,
    "nationality": "Norfolk Island",
    "profession": "engineer"
  },
  {
    "firstName": "Nichole",
    "lastName": "Ryan",
    "age": 38,
    "nationality": "Uganda",
    "profession": "astronaut"
  },
  {
    "firstName": "Orpha",
    "lastName": "Dach",
    "age": 32,
    "nationality": "French Southern Territories",
    "profession": "engineer"
  },
  {
    "firstName": "Enos",
    "lastName": "Carter",
    "age": 34,
    "nationality": "Australia",
    "profession": "astronaut"
  },
  {
    "firstName": "Dahlia",
    "lastName": "Predovic",
    "age": 36,
    "nationality": "Croatia",
    "profession": "engineer"
  },
  {
    "firstName": "Sven",
    "lastName": "Franey",
    "age": 37,
    "nationality": "Samoa",
    "profession": "doctor"
  },
  {
    "firstName": "Stephanie",
    "lastName": "Lubowitz",
    "age": 38,
    "nationality": "Vanuatu",
    "profession": "doctor"
  },
  {
    "firstName": "Armando",
    "lastName": "Schimmel",
    "age": 40,
    "nationality": "Grenada",
    "profession": "engineer"
  },
  {
    "firstName": "Wilfredo",
    "lastName": "Bradtke",
    "age": 30,
    "nationality": "Burundi",
    "profession": "engineer"
  },
  {
    "firstName": "Scarlett",
    "lastName": "Collins",
    "age": 33,
    "nationality": "Guyana",
    "profession": "engineer"
  },
  {
    "firstName": "Reynold",
    "lastName": "Little",
    "age": 38,
    "nationality": "Heard Island and McDonald Islands",
    "profession": "engineer"
  },
  {
    "firstName": "Adeline",
    "lastName": "Friesen",
    "age": 39,
    "nationality": "Cuba",
    "profession": "astronaut"
  },
  {
    "firstName": "Zackary",
    "lastName": "Smith",
    "age": 35,
    "nationality": "Virgin Islands, U.S.",
    "profession": "astronaut"
  },
  {
    "firstName": "Marisa",
    "lastName": "Gottlieb",
    "age": 30,
    "nationality": "Saint Lucia",
    "profession": "engineer"
  },
  {
    "firstName": "Richmond",
    "lastName": "Schmitt-Sipes",
    "age": 38,
    "nationality": "Brunei Darussalam",
    "profession": "engineer"
  },
  {
    "firstName": "Joshua",
    "lastName": "Feil",
    "age": 34,
    "nationality": "India",
    "profession": "engineer"
  },
  {
    "firstName": "Trisha",
    "lastName": "Ruecker",
    "age": 34,
    "nationality": "Congo",
    "profession": "astronaut"
  },
  {
    "firstName": "Ben",
    "lastName": "Nienow-Kuphal",
    "age": 30,
    "nationality": "Austria",
    "profession": "astronaut"
  },
  {
    "firstName": "Taya",
    "lastName": "Barton",
    "age": 31,
    "nationality": "Egypt",
    "profession": "doctor"
  },
  {
    "firstName": "Jalyn",
    "lastName": "Littel",
    "age": 32,
    "nationality": "Mozambique",
    "profession": "astronaut"
  },
  {
    "firstName": "Collin",
    "lastName": "Koch",
    "age": 30,
    "nationality": "Andorra",
    "profession": "doctor"
  },
  {
    "firstName": "Enrique",
    "lastName": "Gibson",
    "age": 34,
    "nationality": "Virgin Islands, British",
    "profession": "engineer"
  },
  {
    "firstName": "Bria",
    "lastName": "Ebert",
    "age": 34,
    "nationality": "Tonga",
    "profession": "doctor"
  },
  {
    "firstName": "Alvina",
    "lastName": "Klein",
    "age": 32,
    "nationality": "Barbados",
    "profession": "doctor"
  },
  {
    "firstName": "Garnett",
    "lastName": "Hintz",
    "age": 34,
    "nationality": "Comoros",
    "profession": "doctor"
  },
  {
    "firstName": "Violette",
    "lastName": "Zboncak",
    "age": 33,
    "nationality": "Latvia",
    "profession": "engineer"
  },
  {
    "firstName": "Walton",
    "lastName": "Goldner",
    "age": 32,
    "nationality": "New Zealand",
    "profession": "doctor"
  },
  {
    "firstName": "Elva",
    "lastName": "Schuppe",
    "age": 32,
    "nationality": "Serbia",
    "profession": "engineer"
  },
  {
    "firstName": "Birdie",
    "lastName": "Lynch",
    "age": 39,
    "nationality": "Nicaragua",
    "profession": "engineer"
  },
  {
    "firstName": "Major",
    "lastName": "Hettinger",
    "age": 39,
    "nationality": "Martinique",
    "profession": "doctor"
  },
  {
    "firstName": "Enid",
    "lastName": "Cormier",
    "age": 39,
    "nationality": "Estonia",
    "profession": "astronaut"
  },
  {
    "firstName": "Stephania",
    "lastName": "Gleichner",
    "age": 33,
    "nationality": "Tanzania",
    "profession": "engineer"
  },
  {
    "firstName": "Trisha",
    "lastName": "Ruecker",
    "age": 34,
    "nationality": "Congo",
    "profession": "astronaut"
  },
  {
    "firstName": "Ben",
    "lastName": "Nienow-Kuphal",
    "age": 30,
    "nationality": "Austria",
    "profession": "astronaut"
  }
]
